imager200_python_sdk/__init__.py
imager200_python_sdk/api_client.py
imager200_python_sdk/api_response.py
imager200_python_sdk/configuration.py
imager200_python_sdk/exceptions.py
imager200_python_sdk/py.typed
imager200_python_sdk/rest.py
imager200_python_sdk/api/__init__.py
imager200_python_sdk/api/blend_api.py
imager200_python_sdk/api/blur_api.py
imager200_python_sdk/api/blurhash_api.py
imager200_python_sdk/api/blurpartial_api.py
imager200_python_sdk/api/brightness_api.py
imager200_python_sdk/api/compress_api.py
imager200_python_sdk/api/concat_api.py
imager200_python_sdk/api/contrast_api.py
imager200_python_sdk/api/convert_api.py
imager200_python_sdk/api/crop_api.py
imager200_python_sdk/api/equalize_api.py
imager200_python_sdk/api/grayscale_api.py
imager200_python_sdk/api/imageinfo_api.py
imager200_python_sdk/api/pipeline_api.py
imager200_python_sdk/api/resize_api.py
imager200_python_sdk/api/rotate_api.py
imager200_python_sdk/api/text_api.py
imager200_python_sdk/models/__init__.py
imager200_python_sdk/models/blend_request.py
imager200_python_sdk/models/concat_request.py
imager200_python_sdk/models/error_response.py
imager200_python_sdk/models/image_metadata.py
imager200_python_sdk/models/info_response.py
imager200_python_sdk/models/pipeline_execution_result.py
imager200_python_sdk/models/pipeline_status.py
imager200_python_sdk/models/success_response.py
imager200_python_sdk-1.0.1.dist-info/METADATA
imager200_python_sdk-1.0.1.dist-info/WHEEL
imager200_python_sdk-1.0.1.dist-info/top_level.txt
imager200_python_sdk-1.0.1.dist-info/RECORD
