Metadata-Version: 2.1
Name: imager200-python-sdk
Version: 1.0.1
Summary: bindings for interacting with the imager200 API in Python
Home-page: 
Author: OpenAPI Generator community
Author-email: contact@imager200.io
Keywords: imager200 API,image processing,OpenAPI,OpenAPI-Generator
Requires-Dist: urllib3 <2.1.0,>=1.25.3
Requires-Dist: python-dateutil
Requires-Dist: pydantic >=2
Requires-Dist: typing-extensions >=4.7.1
